{"Q1": "<br> totally </br> agree", "Q0": "<br> disagree </br> very much", "Q3": "<br> agree </br> very much", "Q2": "<br> agree </br> very much", "Q5": "<br> agree </br> very much", "Q4": "<br> neutral", "Q7": "<br> disagree </br> very much", "Q6": "<br> agree </br> slightly", "Q9": "<br> agree </br> slightly", "Q8": "<br> agree </br> slightly", "Q27": "<br> agree </br> slightly", "Q34": "<br> disagree </br> very much", "Q36": "<br> neutral", "Q37": "<br> disagree </br> slightly", "Q30": "<br> disagree </br> very much", "Q29": "<br> totally </br> agree", "Q32": "<br> agree </br> very much", "Q20": "<br> agree </br> very much", "Q25": "<br> agree </br> very much", "Q40": "<br> totally </br> agree", "Q31": "<br> agree </br> slightly", "Q21": "<br> agree </br> very much", "Q26": "<br> agree </br> very much", "Q41": "<br> agree </br> slightly", "Q38": "<br> disagree </br> very much", "Q22": "<br> disagree </br> very much", "Q35": "<br> agree </br> slightly", "Q15": "<br> totally </br> agree", "Q14": "<br> disagree </br> slightly", "Q17": "<br> agree </br> very much", "Q16": "<br> agree </br> slightly", "Q11": "<br> agree </br> very much", "Q10": "<br> disagree </br> slightly", "Q13": "<br> disagree </br> slightly", "Q12": "<br> totally </br> disagree", "Q28": "<br> totally </br> agree", "Q24": "<br> totally </br> agree", "Q39": "<br> agree </br> slightly", "Q33": "<br> agree </br> slightly", "Q19": "<br> agree </br> slightly", "Q18": "<br> agree </br> slightly", "Q23": "<br> agree </br> slightly"}