{"Q15": "</br> a little bit", "Q14": "</br> quite a bit", "Q17": "</br> moderately", "Q16": "</br> quite a bit", "Q11": "</br> a little bit", "Q10": "</br> a little bit", "Q13": "</br> moderately", "Q12": "</br> quite a bit", "Q19": "</br> quite a bit", "Q18": "</br> moderately", "Q44": "</br> not at all", "Q42": "</br> moderately", "Q43": "</br> a little bit", "Q40": "</br> moderately", "Q41": "</br> a little bit", "Q1": "</br> quite a bit", "Q0": "</br> a little bit", "Q3": "</br> a little bit", "Q2": "</br> moderately", "Q5": "</br> quite a bit", "Q4": "</br> not at all", "Q7": "</br> a little bit", "Q6": "</br> quite a bit", "Q9": "</br> moderately", "Q8": "</br> a little bit", "Q33": "</br> moderately", "Q32": "</br> not at all", "Q31": "</br> a little bit", "Q30": "</br> quite a bit", "Q37": "</br> moderately", "Q36": "</br> a little bit", "Q35": "</br> moderately", "Q34": "</br> moderately", "Q39": "</br> moderately", "Q38": "</br> quite a bit", "Q20": "</br> not at all", "Q21": "</br> moderately", "Q22": "</br> a little bit", "Q23": "</br> a little bit", "Q24": "</br> a little bit", "Q25": "</br> quite a bit", "Q26": "</br> a little bit", "Q27": "</br> quite a bit", "Q28": "</br> not at all", "Q29": "</br> quite a bit"}